heagVehicleLivedataUtils/__init__.py
heagVehicleLivedataUtils/apiUtils.py
heagVehicleLivedataUtils/vehicleInformation.py
heagVehicleLivedataUtils/analyze/__init__.py
heagVehicleLivedataUtils/analyze/data.py
heagVehicleLivedataUtils/analyze/plot.py
heagVehicleLivedataUtils/vehicleDataUtils/__init__.py
heagVehicleLivedataUtils/vehicleDataUtils/process.py
heagVehicleLivedataUtils/vehicleDataUtils/read.py
heagvehiclelivedatautils-0.1.4.dist-info/METADATA
heagvehiclelivedatautils-0.1.4.dist-info/WHEEL
heagvehiclelivedatautils-0.1.4.dist-info/licenses/LICENSE
heagvehiclelivedatautils-0.1.4.dist-info/RECORD
