Metadata-Version: 2.4
Name: heagVehicleLivedataUtils
Version: 0.1.4
Summary: some tools for working with vehicle livedata for trams in darmstadt
Author-email: saski <git.sar@coors-online.de>
License-File: LICENSE
Classifier: License :: OSI Approved :: MIT License
Classifier: Operating System :: OS Independent
Classifier: Programming Language :: Python :: 3
Requires-Python: >=3.8
Requires-Dist: matplotlib
Requires-Dist: pandas
Requires-Dist: requests
Requires-Dist: seaborn
